README.md
setup.cfg
setup.py
ie_mbdbl2018_leticiajaramillo/__init__.py
ie_mbdbl2018_leticiajaramillo.egg-info/PKG-INFO
ie_mbdbl2018_leticiajaramillo.egg-info/SOURCES.txt
ie_mbdbl2018_leticiajaramillo.egg-info/dependency_links.txt
ie_mbdbl2018_leticiajaramillo.egg-info/not-zip-safe
ie_mbdbl2018_leticiajaramillo.egg-info/top_level.txt