Metadata-Version: 1.0
Name: ie-mbdbl2018-leticiajaramillo
Version: 0.1
Summary: Python Packaging Starting Kit - Simple Structure to creater your own package - for training purposes!
Home-page: https://github.com/Leticiajaramillo/ie_mbdbl2018_leticiajaramillo
Author: Leticia Jaramillo
Author-email: leticiajaramillo@student.ie.edu
License: MIT
Platform: UNKNOWN
